emc2/__init__.py
emc2/core/__init__.py
emc2/core/instrument.py
emc2/core/instruments.py
emc2/core/model.py
emc2/core/bulk_c6_tables/bulk_1064nm_C6PSD_c6_8col_ice_agg_rough_270K.dat
emc2/core/bulk_c6_tables/bulk_1064nm_C6PSD_mie_ice.dat
emc2/core/bulk_c6_tables/bulk_1064nm_C6PSD_mie_liq.dat
emc2/core/bulk_c6_tables/bulk_1064nm_C6PSD_mie_liq_c.dat
emc2/core/bulk_c6_tables/bulk_CEIL_C6PSD_c6_8col_ice_agg_rough_270K.dat
emc2/core/bulk_c6_tables/bulk_CEIL_C6PSD_mie_ice.dat
emc2/core/bulk_c6_tables/bulk_CEIL_C6PSD_mie_liq.dat
emc2/core/bulk_c6_tables/bulk_CEIL_C6PSD_mie_liq_c.dat
emc2/core/bulk_c6_tables/bulk_CSAPR_C6PSD_c6_8col_ice_agg_rough_270K.dat
emc2/core/bulk_c6_tables/bulk_CSAPR_C6PSD_mie_ice.dat
emc2/core/bulk_c6_tables/bulk_CSAPR_C6PSD_mie_liq.dat
emc2/core/bulk_c6_tables/bulk_CSAPR_C6PSD_mie_liq_c.dat
emc2/core/bulk_c6_tables/bulk_HSRL_C6PSD_c6_8col_ice_agg_rough_270K.dat
emc2/core/bulk_c6_tables/bulk_HSRL_C6PSD_mie_ice.dat
emc2/core/bulk_c6_tables/bulk_HSRL_C6PSD_mie_liq.dat
emc2/core/bulk_c6_tables/bulk_KAZR_C6PSD_c6_8col_ice_agg_rough_270K.dat
emc2/core/bulk_c6_tables/bulk_KAZR_C6PSD_mie_ice.dat
emc2/core/bulk_c6_tables/bulk_KAZR_C6PSD_mie_liq.dat
emc2/core/bulk_c6_tables/bulk_KAZR_C6PSD_mie_liq_c.dat
emc2/core/bulk_c6_tables/bulk_NEXRAD_C6PSD_c6_8col_ice_agg_rough_270K.dat
emc2/core/bulk_c6_tables/bulk_NEXRAD_C6PSD_mie_ice.dat
emc2/core/bulk_c6_tables/bulk_NEXRAD_C6PSD_mie_liq.dat
emc2/core/bulk_c6_tables/bulk_NEXRAD_C6PSD_mie_liq_c.dat
emc2/core/bulk_c6_tables/bulk_RL_C6PSD_c6_8col_ice_agg_rough_270K.dat
emc2/core/bulk_c6_tables/bulk_RL_C6PSD_mie_ice.dat
emc2/core/bulk_c6_tables/bulk_RL_C6PSD_mie_liq.dat
emc2/core/bulk_c6_tables/bulk_WACR_C6PSD_c6_8col_ice_agg_rough_270K.dat
emc2/core/bulk_c6_tables/bulk_WACR_C6PSD_mie_ice.dat
emc2/core/bulk_c6_tables/bulk_WACR_C6PSD_mie_liq.dat
emc2/core/bulk_c6_tables/bulk_WACR_C6PSD_mie_liq_c.dat
emc2/core/bulk_c6_tables/bulk_XSACR_C6PSD_c6_8col_ice_agg_rough_270K.dat
emc2-1.3.5.dist-info/licenses/LICENSE
emc2-1.3.5.dist-info/METADATA
emc2-1.3.5.dist-info/WHEEL
emc2-1.3.5.dist-info/top_level.txt
emc2-1.3.5.dist-info/RECORD
