Metadata-Version: 2.4
Name: emc2
Version: 1.3.5
Summary: An open source framework for atmospheric model evaluation using observational data
Home-page: https://github.com/ARM-DOE/EMC2
Author: Robert Jackson
Author-email: rjackson@anl.gov
License: MIT
Classifier: Development Status :: 5 - Production/Stable
Classifier: License :: OSI Approved :: MIT License
Classifier: Programming Language :: Python
Classifier: Programming Language :: Python :: 3.10
Classifier: Programming Language :: Python :: 3.11
Classifier: Programming Language :: Python :: 3.12
Classifier: Programming Language :: Python :: 3.13
License-File: LICENSE
Dynamic: author
Dynamic: author-email
Dynamic: classifier
Dynamic: description
Dynamic: home-page
Dynamic: license
Dynamic: license-file
Dynamic: summary
